iscc_sdk/__init__.py
iscc_sdk/audio.py
iscc_sdk/cli.py
iscc_sdk/compat.py
iscc_sdk/container.py
iscc_sdk/docx_.py
iscc_sdk/epub.py
iscc_sdk/exceptions.py
iscc_sdk/image.py
iscc_sdk/install.py
iscc_sdk/ipfs.py
iscc_sdk/main.py
iscc_sdk/mediatype.py
iscc_sdk/metadata.py
iscc_sdk/monkeys.py
iscc_sdk/mp7.py
iscc_sdk/options.py
iscc_sdk/pdf.py
iscc_sdk/text.py
iscc_sdk/thumbnail.py
iscc_sdk/tools.py
iscc_sdk/utils.py
iscc_sdk/video.py
iscc_sdk-0.8.5.dist-info/entry_points.txt
iscc_sdk-0.8.5.dist-info/LICENSE
iscc_sdk-0.8.5.dist-info/METADATA
iscc_sdk-0.8.5.dist-info/WHEEL
iscc_sdk-0.8.5.dist-info/RECORD
