Metadata-Version: 2.3
Name: iscc-sdk
Version: 0.8.5
Summary: SDK for creating ISCCs (International Standard Content Codes)
License: Apache-2.0
Keywords: iscc,identifier,media,content,similarity
Author: Titusz
Author-email: tp@py7.de
Requires-Python: >=3.10,<3.14
Classifier: Development Status :: 4 - Beta
Classifier: Intended Audience :: Developers
Classifier: Intended Audience :: Science/Research
Classifier: License :: OSI Approved :: Apache Software License
Classifier: Natural Language :: English
Classifier: Operating System :: OS Independent
Classifier: Programming Language :: Cython
Classifier: Programming Language :: Python :: 3
Classifier: Programming Language :: Python :: 3.10
Classifier: Programming Language :: Python :: 3.11
Classifier: Programming Language :: Python :: 3.12
Classifier: Programming Language :: Python :: 3.13
Classifier: Topic :: Multimedia
Classifier: Topic :: Multimedia :: Graphics
Classifier: Topic :: Multimedia :: Sound/Audio
Classifier: Topic :: Multimedia :: Video
Classifier: Topic :: Scientific/Engineering :: Image Recognition
Classifier: Topic :: Scientific/Engineering :: Information Analysis
Classifier: Topic :: Software Development :: Libraries :: Python Modules
Classifier: Topic :: Text Processing :: Indexing
Provides-Extra: sci
Provides-Extra: sct
Requires-Dist: Pillow
Requires-Dist: bleach
Requires-Dist: click (<=8.1.8)
Requires-Dist: cython
Requires-Dist: ebookmeta
Requires-Dist: exiv2
Requires-Dist: extractous
Requires-Dist: iscc-core
Requires-Dist: iscc-schema
Requires-Dist: iscc-sci ; extra == "sci"
Requires-Dist: iscc-sct ; extra == "sct"
Requires-Dist: jmespath
Requires-Dist: langcodes
Requires-Dist: numpy
Requires-Dist: onnxruntime (<1.22.0) ; extra == "sci" or extra == "sct"
Requires-Dist: pdftext
Requires-Dist: pikepdf
Requires-Dist: pillow-avif-plugin
Requires-Dist: pillow-heif
Requires-Dist: platformdirs
Requires-Dist: pymupdf
Requires-Dist: pytaglib
Requires-Dist: python-docx
Requires-Dist: python-magic-pure
Requires-Dist: typer
Project-URL: Bug Tracker, https://github.com/iscc/iscc-sdk/issues
Project-URL: Changelog, https://sdk.iscc.codes/changelog
Project-URL: Coverage, https://app.codecov.io/gh/iscc/iscc-sdk
Project-URL: Donate, https://iscc.foundation/support
Project-URL: Homepage, https://sdk.iscc.codes
Project-URL: Repository, https://github.com/iscc/iscc-sdk
Project-URL: Twitter, https://twitter.com/iscc_foundation
